aquilapy/__init__.py
aquilapy/aquiladb.py
aquilapy/aquilahub.py
aquilapy/wallet.py
aquilapy-0.3.1.dist-info/LICENSE
aquilapy-0.3.1.dist-info/METADATA
aquilapy-0.3.1.dist-info/WHEEL
aquilapy-0.3.1.dist-info/top_level.txt
aquilapy-0.3.1.dist-info/RECORD
