Metadata-Version: 2.1
Name: aquilapy
Version: 0.3.1
Summary: Python client library for Aquila Network
Home-page: https://github.com/Aquila-Network/aquilapy
Author: Aquila Network
Author-email: contact@aquila.network
License: UNKNOWN
Platform: UNKNOWN
Classifier: Programming Language :: Python :: 3
Classifier: License :: OSI Approved :: MIT License
Classifier: Operating System :: OS Independent
Requires-Dist: bson
Requires-Dist: requests
Requires-Dist: pycryptodome
Requires-Dist: base58
